mashcima/Beam.py
mashcima/Canvas.py
mashcima/CanvasOptions.py
mashcima/Config.py
mashcima/DurationDots.py
mashcima/Slur.py
mashcima/Sprite.py
mashcima/SpriteGroup.py
mashcima/SymbolRepository.py
mashcima/__init__.py
mashcima/annotation_to_image.py
mashcima/debug.py
mashcima/delete_files.py
mashcima/generate_random_annotation.py
mashcima/generate_staff_lines.py
mashcima/get_symbols.py
mashcima/primus_adapter.py
mashcima/transform_image.py
mashcima/utils.py
mashcima/vocabulary.py
mashcima/canvas_items/Barline.py
mashcima/canvas_items/BeamedNote.py
mashcima/canvas_items/CanvasItem.py
mashcima/canvas_items/Clef.py
mashcima/canvas_items/FlagNote.py
mashcima/canvas_items/HalfNote.py
mashcima/canvas_items/InvisibleSlurEnd.py
mashcima/canvas_items/KeySignature.py
mashcima/canvas_items/Note.py
mashcima/canvas_items/QuarterNote.py
mashcima/canvas_items/Rest.py
mashcima/canvas_items/SlurableItem.py
mashcima/canvas_items/StemNote.py
mashcima/canvas_items/TimeSignature.py
mashcima/canvas_items/WholeNote.py
mashcima/canvas_items/WholeTimeSignature.py
mashcima/canvas_items/__init__.py
mashcima/default_symbols/__init__.py
mashcima/default_symbols/clef_c.png
mashcima/default_symbols/clef_f.png
mashcima/default_symbols/clef_f.txt
mashcima/default_symbols/clef_g.png
mashcima/default_symbols/clef_g.txt
mashcima/default_symbols/note_eighth_flag_8.png
mashcima/default_symbols/note_eighth_flag_8.txt
mashcima/default_symbols/note_eighth_notehead.png
mashcima/default_symbols/note_eighth_notehead.txt
mashcima/default_symbols/note_eighth_stem.png
mashcima/default_symbols/note_eighth_stem.txt
mashcima/default_symbols/note_sixteenth_flag_16.png
mashcima/default_symbols/note_sixteenth_flag_16.txt
mashcima/default_symbols/note_sixteenth_flag_8.png
mashcima/default_symbols/note_sixteenth_flag_8.txt
mashcima/default_symbols/note_sixteenth_notehead.png
mashcima/default_symbols/note_sixteenth_notehead.txt
mashcima/default_symbols/note_sixteenth_stem.png
mashcima-1.0.0.dist-info/LICENSE
mashcima-1.0.0.dist-info/METADATA
mashcima-1.0.0.dist-info/WHEEL
mashcima-1.0.0.dist-info/top_level.txt
mashcima-1.0.0.dist-info/RECORD
