Metadata-Version: 2.1
Name: mashcima
Version: 1.0.0
Summary: Handwritten music image synthesizer for HMR
Home-page: https://github.com/Jirka-Mayer/Mashcima
Author: Jiří Mayer
Author-email: jirkamayer97@gmail.com
License: UNKNOWN
Project-URL: Bug Tracker, https://github.com/Jirka-Mayer/Mashcima/issues
Platform: UNKNOWN
Classifier: Programming Language :: Python :: 3
Classifier: Natural Language :: English
Classifier: Intended Audience :: Science/Research
Classifier: License :: OSI Approved :: MIT License
Classifier: Operating System :: OS Independent
Requires-Python: >=3.6
License-File: LICENSE
Requires-Dist: numpy (>=1.11.1)
Requires-Dist: opencv-python (>=3.4.8.29)
Requires-Dist: muscima (>=0.10.0)
Requires-Dist: appdirs (>=1.4.4)
Requires-Dist: tqdm (>=4.40.0)
Requires-Dist: requests (>=2.15.1scipy>=1.5.4)
Requires-Dist: scikit-image (>=0.18.0)
